{
  "legislative_session": "2026",
  "identifier": "HB918",
  "title": "PHARMACIES: Provides relative to pharmaceutical costs (OR +$153,127 GF EX See Note)",
  "from_organization": "~{\"classification\": \"lower\"}",
  "classification": [
    "bill"
  ],
  "subject": [],
  "abstracts": [],
  "other_titles": [],
  "other_identifiers": [
    {
      "identifier": "ocd-bill-la-2026-hb918"
    }
  ],
  "actions": [
    {
      "description": "Read by title, under the rules, referred to the Committee on Health and Welfare.",
      "date": "2026-03-09",
      "organization_id": "~{\"classification\": \"lower\"}",
      "classification": [
        "referral-committee"
      ],
      "related_entities": [],
      "_processing": {
        "log_file_created": "2026-07-14T18:58:48Z"
      }
    },
    {
      "description": "First appeared in the Interim Calendar on 2/27/2026.",
      "date": "2026-02-27",
      "organization_id": "~{\"classification\": \"lower\"}",
      "classification": [],
      "related_entities": [],
      "_processing": {
        "log_file_created": "2026-07-14T18:58:48Z"
      }
    },
    {
      "description": "Under the rules, provisionally referred to the Committee on Health and Welfare.",
      "date": "2026-02-27",
      "organization_id": "~{\"classification\": \"lower\"}",
      "classification": [
        "referral-committee"
      ],
      "related_entities": [],
      "_processing": {
        "log_file_created": "2026-07-14T18:58:48Z"
      }
    },
    {
      "description": "Prefiled.",
      "date": "2026-02-27",
      "organization_id": "~{\"classification\": \"lower\"}",
      "classification": [
        "filing"
      ],
      "related_entities": [],
      "_processing": {
        "log_file_created": "2026-07-14T18:58:48Z"
      }
    }
  ],
  "sponsorships": [
    {
      "name": "Jay Galle",
      "classification": "primary",
      "entity_type": "person",
      "primary": true,
      "person_id": "~{\"name\": \"Jay Galle\"}",
      "organization_id": null
    }
  ],
  "related_bills": [],
  "versions": [
    {
      "note": "HB918 Original",
      "links": [
        {
          "url": "https://www.legis.la.gov/Legis/ViewDocument.aspx?d=1447605",
          "media_type": "application/pdf"
        }
      ],
      "date": "",
      "classification": ""
    }
  ],
  "documents": [
    {
      "note": "Digest of HB918 Original",
      "links": [
        {
          "url": "https://www.legis.la.gov/Legis/ViewDocument.aspx?d=1447612",
          "media_type": "application/pdf"
        }
      ],
      "date": "",
      "classification": ""
    }
  ],
  "citations": [],
  "sources": [
    {
      "url": "https://www.legis.la.gov/Legis/BillInfo.aspx?i=250854",
      "note": ""
    }
  ],
  "extras": {},
  "jurisdiction": {
    "id": "ocd-jurisdiction/country:us/state:la/government",
    "name": "Louisiana",
    "classification": "state",
    "division_id": "ocd-division/country:us/state:la"
  },
  "_processing": {
    "logs_latest_update": "2026-07-14T18:58:48Z",
    "text_extraction_latest_update": "2026-07-15T01:32:43.688454Z"
  }
}