{
  "legislative_session": "2026",
  "identifier": "SR152",
  "title": "CONDOLENCES: To express the sincere and heartfelt condolences to the family and friends of Susan Ann Traylor Bittick on the occasion of her passing.",
  "from_organization": "~{\"classification\": \"upper\"}",
  "classification": [
    "resolution"
  ],
  "subject": [],
  "abstracts": [],
  "other_titles": [],
  "other_identifiers": [
    {
      "identifier": "ocd-bill-la-2026-sr152"
    }
  ],
  "actions": [
    {
      "description": "Enrolled.  Signed by the President of the Senate and sent to the Secretary of State by the Secretary of the Senate.",
      "date": "2026-05-28",
      "organization_id": "~{\"classification\": \"upper\"}",
      "classification": [
        "enrolled"
      ],
      "related_entities": [],
      "_processing": {
        "log_file_created": "2026-07-14T18:58:44Z"
      }
    },
    {
      "description": "Introduced in the Senate; read by title.  Rules suspended.  Read second time by title and adopted.",
      "date": "2026-05-25",
      "organization_id": "~{\"classification\": \"upper\"}",
      "classification": [
        "reading-2"
      ],
      "related_entities": [],
      "_processing": {
        "log_file_created": "2026-07-14T18:58:44Z"
      }
    }
  ],
  "sponsorships": [
    {
      "name": "Franklin J. Foil",
      "classification": "primary",
      "entity_type": "person",
      "primary": true,
      "person_id": "~{\"name\": \"Franklin J. Foil\"}",
      "organization_id": null
    }
  ],
  "related_bills": [],
  "versions": [
    {
      "note": "SR152 Enrolled",
      "links": [
        {
          "url": "https://www.legis.la.gov/Legis/ViewDocument.aspx?d=1476159",
          "media_type": "application/pdf"
        }
      ],
      "date": "",
      "classification": ""
    },
    {
      "note": "SR152 Original",
      "links": [
        {
          "url": "https://www.legis.la.gov/Legis/ViewDocument.aspx?d=1476100",
          "media_type": "application/pdf"
        }
      ],
      "date": "",
      "classification": ""
    }
  ],
  "documents": [
    {
      "note": "Resume Digest for SR152",
      "links": [
        {
          "url": "https://www.legis.la.gov/Legis/ViewDocument.aspx?d=1482640",
          "media_type": "application/pdf"
        }
      ],
      "date": "",
      "classification": ""
    },
    {
      "note": "Digest of SR152 Original",
      "links": [
        {
          "url": "https://www.legis.la.gov/Legis/ViewDocument.aspx?d=1476101",
          "media_type": "application/pdf"
        }
      ],
      "date": "",
      "classification": ""
    }
  ],
  "citations": [],
  "sources": [
    {
      "url": "https://www.legis.la.gov/Legis/BillInfo.aspx?i=252072",
      "note": ""
    }
  ],
  "extras": {},
  "jurisdiction": {
    "id": "ocd-jurisdiction/country:us/state:la/government",
    "name": "Louisiana",
    "classification": "state",
    "division_id": "ocd-division/country:us/state:la"
  },
  "_processing": {
    "logs_latest_update": "2026-07-14T18:58:44Z",
    "text_extraction_latest_update": "2026-07-21T12:41:01.522948Z"
  }
}