{
  "legislative_session": "2026",
  "identifier": "HB103",
  "title": "DISTRICTS/TAXING: Provides relative to the Walnut Street Special District in the city of Monroe",
  "from_organization": "~{\"classification\": \"lower\"}",
  "classification": [
    "bill"
  ],
  "subject": [],
  "abstracts": [],
  "other_titles": [],
  "other_identifiers": [
    {
      "identifier": "ocd-bill-la-2026-hb103"
    }
  ],
  "actions": [
    {
      "description": "Read by title, under the rules, referred to the Committee on Municipal, Parochial and Cultural Affairs.",
      "date": "2026-03-09",
      "organization_id": "~{\"classification\": \"lower\"}",
      "classification": [
        "referral-committee"
      ],
      "related_entities": [],
      "_processing": {
        "log_file_created": "2026-07-14T18:58:50Z"
      }
    },
    {
      "description": "First appeared in the Interim Calendar on 2/13/2026.",
      "date": "2026-02-13",
      "organization_id": "~{\"classification\": \"lower\"}",
      "classification": [],
      "related_entities": [],
      "_processing": {
        "log_file_created": "2026-07-14T18:58:50Z"
      }
    },
    {
      "description": "Under the rules, provisionally referred to the Committee on Municipal, Parochial and Cultural Affairs.",
      "date": "2026-02-09",
      "organization_id": "~{\"classification\": \"lower\"}",
      "classification": [
        "referral-committee"
      ],
      "related_entities": [],
      "_processing": {
        "log_file_created": "2026-07-14T18:58:50Z"
      }
    },
    {
      "description": "Prefiled.",
      "date": "2026-02-09",
      "organization_id": "~{\"classification\": \"lower\"}",
      "classification": [
        "filing"
      ],
      "related_entities": [],
      "_processing": {
        "log_file_created": "2026-07-14T18:58:50Z"
      }
    }
  ],
  "sponsorships": [
    {
      "name": "Francis C. Thompson",
      "classification": "primary",
      "entity_type": "person",
      "primary": true,
      "person_id": "~{\"name\": \"Francis C. Thompson\"}",
      "organization_id": null
    }
  ],
  "related_bills": [],
  "versions": [
    {
      "note": "HB103 Original",
      "links": [
        {
          "url": "https://www.legis.la.gov/Legis/ViewDocument.aspx?d=1437544",
          "media_type": "application/pdf"
        }
      ],
      "date": "",
      "classification": ""
    }
  ],
  "documents": [
    {
      "note": "Digest of HB103 Original",
      "links": [
        {
          "url": "https://www.legis.la.gov/Legis/ViewDocument.aspx?d=1437549",
          "media_type": "application/pdf"
        }
      ],
      "date": "",
      "classification": ""
    }
  ],
  "citations": [],
  "sources": [
    {
      "url": "https://www.legis.la.gov/Legis/BillInfo.aspx?i=249735",
      "note": ""
    }
  ],
  "extras": {},
  "jurisdiction": {
    "id": "ocd-jurisdiction/country:us/state:la/government",
    "name": "Louisiana",
    "classification": "state",
    "division_id": "ocd-division/country:us/state:la"
  },
  "_processing": {
    "logs_latest_update": "2026-07-14T18:58:50Z"
  }
}