{
  "legislative_session": "2026",
  "identifier": "HR50",
  "title": "SPECIAL DAY/WEEK/MONTH: Designates March 24, 2026, as Geaux Far Day at the capitol and commends Geaux Far Louisiana for its contributions to early childhood education",
  "from_organization": "~{\"classification\": \"lower\"}",
  "classification": [
    "resolution"
  ],
  "subject": [],
  "abstracts": [],
  "other_titles": [],
  "other_identifiers": [
    {
      "identifier": "ocd-bill-la-2026-hr50"
    }
  ],
  "actions": [
    {
      "description": "Taken by the Clerk of the House and presented to the Secretary of State in accordance with the Rules of the House.",
      "date": "2026-03-27",
      "organization_id": "~{\"classification\": \"lower\"}",
      "classification": [],
      "related_entities": [],
      "_processing": {
        "log_file_created": "2026-07-14T18:58:46Z"
      }
    },
    {
      "description": "Enrolled and signed by the Speaker of the House.",
      "date": "2026-03-25",
      "organization_id": "~{\"classification\": \"lower\"}",
      "classification": [
        "enrolled"
      ],
      "related_entities": [],
      "_processing": {
        "log_file_created": "2026-07-14T18:58:46Z"
      }
    },
    {
      "description": "Read by title, adopted.",
      "date": "2026-03-24",
      "organization_id": "~{\"classification\": \"lower\"}",
      "classification": [],
      "related_entities": [],
      "_processing": {
        "log_file_created": "2026-07-14T18:58:46Z"
      }
    },
    {
      "description": "Read by title.  Lies over under the rules.",
      "date": "2026-03-23",
      "organization_id": "~{\"classification\": \"lower\"}",
      "classification": [],
      "related_entities": [],
      "_processing": {
        "log_file_created": "2026-07-14T18:58:46Z"
      }
    }
  ],
  "sponsorships": [
    {
      "name": "Troy Hebert",
      "classification": "primary",
      "entity_type": "person",
      "primary": true,
      "person_id": "~{\"name\": \"Troy Hebert\"}",
      "organization_id": null
    }
  ],
  "related_bills": [],
  "versions": [
    {
      "note": "HR50 Enrolled",
      "links": [
        {
          "url": "https://www.legis.la.gov/Legis/ViewDocument.aspx?d=1453136",
          "media_type": "application/pdf"
        }
      ],
      "date": "",
      "classification": ""
    },
    {
      "note": "HR50 Original",
      "links": [
        {
          "url": "https://www.legis.la.gov/Legis/ViewDocument.aspx?d=1452541",
          "media_type": "application/pdf"
        }
      ],
      "date": "",
      "classification": ""
    }
  ],
  "documents": [
    {
      "note": "Digest of HR50 Original",
      "links": [
        {
          "url": "https://www.legis.la.gov/Legis/ViewDocument.aspx?d=1452542",
          "media_type": "application/pdf"
        }
      ],
      "date": "",
      "classification": ""
    }
  ],
  "citations": [],
  "sources": [
    {
      "url": "https://www.legis.la.gov/Legis/BillInfo.aspx?i=251143",
      "note": ""
    }
  ],
  "extras": {},
  "jurisdiction": {
    "id": "ocd-jurisdiction/country:us/state:la/government",
    "name": "Louisiana",
    "classification": "state",
    "division_id": "ocd-division/country:us/state:la"
  },
  "_processing": {
    "logs_latest_update": "2026-07-14T18:58:46Z",
    "text_extraction_latest_update": "2026-07-21T13:42:39.575462Z"
  }
}