{
  "legislative_session": "2026",
  "identifier": "SB398",
  "title": "HOUSING: Provides relative to the regulation of manufactured housing. (1/1/27) (EN +$40,000 SG RV See Note)",
  "from_organization": "~{\"classification\": \"upper\"}",
  "classification": [
    "bill"
  ],
  "subject": [],
  "abstracts": [],
  "other_titles": [],
  "other_identifiers": [
    {
      "identifier": "ocd-bill-la-2026-sb398"
    }
  ],
  "actions": [
    {
      "description": "Effective date 1/1/2027.",
      "date": "2026-06-02",
      "organization_id": "~{\"classification\": \"upper\"}",
      "classification": [],
      "related_entities": [],
      "_processing": {
        "log_file_created": "2026-07-14T18:58:44Z"
      }
    },
    {
      "description": "Signed by the Governor. Becomes Act No. 765.",
      "date": "2026-06-02",
      "organization_id": "~{\"classification\": \"upper\"}",
      "classification": [
        "became-law",
        "executive-signature"
      ],
      "related_entities": [],
      "_processing": {
        "log_file_created": "2026-07-14T18:58:44Z"
      }
    },
    {
      "description": "Sent to the Governor by the Secretary of the Senate.",
      "date": "2026-05-29",
      "organization_id": "~{\"classification\": \"upper\"}",
      "classification": [
        "executive-receipt"
      ],
      "related_entities": [],
      "_processing": {
        "log_file_created": "2026-07-14T18:58:44Z"
      }
    },
    {
      "description": "Signed by the Speaker of the House.",
      "date": "2026-05-29",
      "organization_id": "~{\"classification\": \"lower\"}",
      "classification": [],
      "related_entities": [],
      "_processing": {
        "log_file_created": "2026-07-14T18:58:44Z"
      }
    },
    {
      "description": "Enrolled.  Signed by the President of the Senate.",
      "date": "2026-05-28",
      "organization_id": "~{\"classification\": \"upper\"}",
      "classification": [
        "enrolled"
      ],
      "related_entities": [],
      "_processing": {
        "log_file_created": "2026-07-14T18:58:44Z"
      }
    },
    {
      "description": "Amendments proposed by the House read and concurred in by a vote of 36 yeas and 0 nays.",
      "date": "2026-05-27",
      "organization_id": "~{\"classification\": \"upper\"}",
      "classification": [],
      "related_entities": [],
      "_processing": {
        "log_file_created": "2026-07-14T18:58:44Z"
      }
    },
    {
      "description": "Received from the House with amendments.",
      "date": "2026-05-26",
      "organization_id": "~{\"classification\": \"upper\"}",
      "classification": [
        "receipt"
      ],
      "related_entities": [],
      "_processing": {
        "log_file_created": "2026-07-14T18:58:44Z"
      }
    },
    {
      "description": "Read third time by title, amended, roll called on final passage, yeas 96, nays 0.  The bill, having received two-thirds vote of the elected members, was finally passed, ordered to the Senate.",
      "date": "2026-05-26",
      "organization_id": "~{\"classification\": \"lower\"}",
      "classification": [
        "passage"
      ],
      "related_entities": [],
      "_processing": {
        "log_file_created": "2026-07-14T18:58:44Z"
      }
    },
    {
      "description": "Scheduled for floor debate on 05/26/2026.",
      "date": "2026-05-25",
      "organization_id": "~{\"classification\": \"lower\"}",
      "classification": [],
      "related_entities": [],
      "_processing": {
        "log_file_created": "2026-07-14T18:58:44Z"
      }
    },
    {
      "description": "Read by title, amended, passed to 3rd reading.",
      "date": "2026-05-20",
      "organization_id": "~{\"classification\": \"lower\"}",
      "classification": [
        "reading-3"
      ],
      "related_entities": [],
      "_processing": {
        "log_file_created": "2026-07-14T18:58:44Z"
      }
    },
    {
      "description": "Reported with Legislative Bureau amendments.",
      "date": "2026-05-19",
      "organization_id": "~{\"classification\": \"lower\"}",
      "classification": [],
      "related_entities": [],
      "_processing": {
        "log_file_created": "2026-07-14T18:58:44Z"
      }
    },
    {
      "description": "Reported with amendments (17-0). Referred to the Legislative Bureau.",
      "date": "2026-05-18",
      "organization_id": "~{\"classification\": \"lower\"}",
      "classification": [
        "committee-passage-favorable"
      ],
      "related_entities": [],
      "_processing": {
        "log_file_created": "2026-07-14T18:58:44Z"
      }
    },
    {
      "description": "Read by title, amended, recommitted to the Committee on Appropriations.",
      "date": "2026-05-12",
      "organization_id": "~{\"classification\": \"lower\"}",
      "classification": [],
      "related_entities": [],
      "_processing": {
        "log_file_created": "2026-07-14T18:58:44Z"
      }
    },
    {
      "description": "Reported with amendments (12-0). To be recommitted to the Committee on Appropriations.",
      "date": "2026-05-11",
      "organization_id": "~{\"classification\": \"lower\"}",
      "classification": [
        "committee-passage-favorable"
      ],
      "related_entities": [],
      "_processing": {
        "log_file_created": "2026-07-14T18:58:44Z"
      }
    },
    {
      "description": "Read by title, under the rules, referred to the Committee on Commerce.",
      "date": "2026-05-05",
      "organization_id": "~{\"classification\": \"lower\"}",
      "classification": [
        "referral-committee"
      ],
      "related_entities": [],
      "_processing": {
        "log_file_created": "2026-07-14T18:58:44Z"
      }
    },
    {
      "description": "Received in the House from the Senate, read by title, lies over under the rules.",
      "date": "2026-04-29",
      "organization_id": "~{\"classification\": \"lower\"}",
      "classification": [],
      "related_entities": [],
      "_processing": {
        "log_file_created": "2026-07-14T18:58:44Z"
      }
    },
    {
      "description": "Senate floor amendments read and adopted.  Read by title and passed by a vote of 38 yeas and 0 nays; ordered reengrossed and sent to the House.  Motion to reconsider tabled.",
      "date": "2026-04-28",
      "organization_id": "~{\"classification\": \"upper\"}",
      "classification": [
        "passage"
      ],
      "related_entities": [],
      "_processing": {
        "log_file_created": "2026-07-14T18:58:44Z"
      }
    },
    {
      "description": "Read by title.  Committee amendments read and adopted. Ordered engrossed and passed to third reading and final passage.",
      "date": "2026-04-27",
      "organization_id": "~{\"classification\": \"upper\"}",
      "classification": [],
      "related_entities": [],
      "_processing": {
        "log_file_created": "2026-07-14T18:58:44Z"
      }
    },
    {
      "description": "Reported with amendments.",
      "date": "2026-04-22",
      "organization_id": "~{\"classification\": \"upper\"}",
      "classification": [
        "committee-passage-favorable"
      ],
      "related_entities": [],
      "_processing": {
        "log_file_created": "2026-07-14T18:58:44Z"
      }
    },
    {
      "description": "Introduced in the Senate; read by title.  Rules suspended.  Read second time and referred to the Committee on Commerce, Consumer Protection and International Affairs.",
      "date": "2026-03-09",
      "organization_id": "~{\"classification\": \"upper\"}",
      "classification": [
        "referral-committee"
      ],
      "related_entities": [],
      "_processing": {
        "log_file_created": "2026-07-14T18:58:44Z"
      }
    },
    {
      "description": "Prefiled and under the rules provisionally referred to the Committee on Commerce, Consumer Protection and International Affairs.",
      "date": "2026-02-27",
      "organization_id": "~{\"classification\": \"upper\"}",
      "classification": [
        "filing",
        "referral-committee"
      ],
      "related_entities": [],
      "_processing": {
        "log_file_created": "2026-07-14T18:58:44Z"
      }
    }
  ],
  "sponsorships": [
    {
      "name": "Franklin J. Foil",
      "classification": "primary",
      "entity_type": "person",
      "primary": true,
      "person_id": "~{\"name\": \"Franklin J. Foil\"}",
      "organization_id": null
    }
  ],
  "related_bills": [],
  "versions": [
    {
      "note": "SB398 Act",
      "links": [
        {
          "url": "https://www.legis.la.gov/Legis/ViewDocument.aspx?d=1480444",
          "media_type": "application/pdf"
        }
      ],
      "date": "",
      "classification": ""
    },
    {
      "note": "SB398 Enrolled",
      "links": [
        {
          "url": "https://www.legis.la.gov/Legis/ViewDocument.aspx?d=1477564",
          "media_type": "application/pdf"
        }
      ],
      "date": "",
      "classification": ""
    },
    {
      "note": "SB398 Reengrossed",
      "links": [
        {
          "url": "https://www.legis.la.gov/Legis/ViewDocument.aspx?d=1467237",
          "media_type": "application/pdf"
        }
      ],
      "date": "",
      "classification": ""
    },
    {
      "note": "SB398 Engrossed",
      "links": [
        {
          "url": "https://www.legis.la.gov/Legis/ViewDocument.aspx?d=1465198",
          "media_type": "application/pdf"
        }
      ],
      "date": "",
      "classification": ""
    },
    {
      "note": "SB398 Original",
      "links": [
        {
          "url": "https://www.legis.la.gov/Legis/ViewDocument.aspx?d=1447843",
          "media_type": "application/pdf"
        }
      ],
      "date": "",
      "classification": ""
    },
    {
      "note": "Senate Floor Amendment, #2787, Foil, Proposed",
      "links": [
        {
          "url": "https://www.legis.la.gov/Legis/ViewDocument.aspx?d=1466484",
          "media_type": "application/pdf"
        }
      ],
      "date": "",
      "classification": ""
    },
    {
      "note": "House Floor Amendment, #6129, Melerine, Adopted",
      "links": [
        {
          "url": "https://www.legis.la.gov/Legis/ViewDocument.aspx?d=1476733",
          "media_type": "application/pdf"
        }
      ],
      "date": "",
      "classification": ""
    },
    {
      "note": "House Floor Amendment, #5968, Melerine, Withdrawn",
      "links": [
        {
          "url": "https://www.legis.la.gov/Legis/ViewDocument.aspx?d=1475518",
          "media_type": "application/pdf"
        }
      ],
      "date": "",
      "classification": ""
    },
    {
      "note": "House Legislative Bureau Amendment, #4025, BUREAU, Adopted",
      "links": [
        {
          "url": "https://www.legis.la.gov/Legis/ViewDocument.aspx?d=1473803",
          "media_type": "application/pdf"
        }
      ],
      "date": "",
      "classification": ""
    },
    {
      "note": "House Committee Amendment, #5714, APP, Adopted",
      "links": [
        {
          "url": "https://www.legis.la.gov/Legis/ViewDocument.aspx?d=1473261",
          "media_type": "application/pdf"
        }
      ],
      "date": "",
      "classification": ""
    },
    {
      "note": "House Floor Amendment, #5618, Villio, Adopted",
      "links": [
        {
          "url": "https://www.legis.la.gov/Legis/ViewDocument.aspx?d=1472815",
          "media_type": "application/pdf"
        }
      ],
      "date": "",
      "classification": ""
    },
    {
      "note": "House Committee Amendment, #5566, APP, Draft",
      "links": [
        {
          "url": "https://www.legis.la.gov/Legis/ViewDocument.aspx?d=1472248",
          "media_type": "application/pdf"
        }
      ],
      "date": "",
      "classification": ""
    },
    {
      "note": "House Committee Amendment, #5343, COM, Adopted",
      "links": [
        {
          "url": "https://www.legis.la.gov/Legis/ViewDocument.aspx?d=1470935",
          "media_type": "application/pdf"
        }
      ],
      "date": "",
      "classification": ""
    },
    {
      "note": "House Committee Amendment, #5258, COM, Draft",
      "links": [
        {
          "url": "https://www.legis.la.gov/Legis/ViewDocument.aspx?d=1470366",
          "media_type": "application/pdf"
        }
      ],
      "date": "",
      "classification": ""
    },
    {
      "note": "House Committee Amendment, #5257, COM, Draft",
      "links": [
        {
          "url": "https://www.legis.la.gov/Legis/ViewDocument.aspx?d=1470262",
          "media_type": "application/pdf"
        }
      ],
      "date": "",
      "classification": ""
    },
    {
      "note": "Senate Floor Bureau Note, #2814, Foil, Adopted",
      "links": [
        {
          "url": "https://www.legis.la.gov/Legis/ViewDocument.aspx?d=1466698",
          "media_type": "application/pdf"
        }
      ],
      "date": "",
      "classification": ""
    },
    {
      "note": "Senate Floor Legislative Bureau Amendment, #2767, Miller, G., Adopted",
      "links": [
        {
          "url": "https://www.legis.la.gov/Legis/ViewDocument.aspx?d=1466148",
          "media_type": "application/pdf"
        }
      ],
      "date": "",
      "classification": ""
    },
    {
      "note": "Senate Committee Amendment, #2536, COM, Adopted",
      "links": [
        {
          "url": "https://www.legis.la.gov/Legis/ViewDocument.aspx?d=1465066",
          "media_type": "application/pdf"
        }
      ],
      "date": "",
      "classification": ""
    },
    {
      "note": "Senate Committee Amendment, #2151, COM, Draft",
      "links": [
        {
          "url": "https://www.legis.la.gov/Legis/ViewDocument.aspx?d=1462537",
          "media_type": "application/pdf"
        }
      ],
      "date": "",
      "classification": ""
    }
  ],
  "documents": [
    {
      "note": "Summary of House Amendments to SB398",
      "links": [
        {
          "url": "https://www.legis.la.gov/Legis/ViewDocument.aspx?d=1477209",
          "media_type": "application/pdf"
        }
      ],
      "date": "",
      "classification": ""
    },
    {
      "note": "House Committee Redigest of SB398 [2]",
      "links": [
        {
          "url": "https://www.legis.la.gov/Legis/ViewDocument.aspx?d=1473259",
          "media_type": "application/pdf"
        }
      ],
      "date": "",
      "classification": ""
    },
    {
      "note": "House Committee Redigest of SB398",
      "links": [
        {
          "url": "https://www.legis.la.gov/Legis/ViewDocument.aspx?d=1470925",
          "media_type": "application/pdf"
        }
      ],
      "date": "",
      "classification": ""
    },
    {
      "note": "Digest of SB398 Reengrossed",
      "links": [
        {
          "url": "https://www.legis.la.gov/Legis/ViewDocument.aspx?d=1467432",
          "media_type": "application/pdf"
        }
      ],
      "date": "",
      "classification": ""
    },
    {
      "note": "Digest of SB398 Engrossed",
      "links": [
        {
          "url": "https://www.legis.la.gov/Legis/ViewDocument.aspx?d=1466644",
          "media_type": "application/pdf"
        }
      ],
      "date": "",
      "classification": ""
    },
    {
      "note": "Digest of SB398 Original",
      "links": [
        {
          "url": "https://www.legis.la.gov/Legis/ViewDocument.aspx?d=1447846",
          "media_type": "application/pdf"
        }
      ],
      "date": "",
      "classification": ""
    }
  ],
  "citations": [],
  "sources": [
    {
      "url": "https://www.legis.la.gov/Legis/BillInfo.aspx?i=250957",
      "note": ""
    }
  ],
  "extras": {},
  "jurisdiction": {
    "id": "ocd-jurisdiction/country:us/state:la/government",
    "name": "Louisiana",
    "classification": "state",
    "division_id": "ocd-division/country:us/state:la"
  },
  "_processing": {
    "logs_latest_update": "2026-07-14T18:58:44Z",
    "text_extraction_latest_update": "2026-07-21T07:13:26.624591Z"
  }
}